ayla_iot_unofficial/__init__.py
ayla_iot_unofficial/ayla_iot_unofficial.py
ayla_iot_unofficial/const.py
ayla_iot_unofficial/device.py
ayla_iot_unofficial/exc.py
ayla_iot_unofficial/fujitsu_consts.py
ayla_iot_unofficial/fujitsu_hvac.py
ayla_iot_unofficial_crevetor-1.3.2.dist-info/LICENSE
ayla_iot_unofficial_crevetor-1.3.2.dist-info/METADATA
ayla_iot_unofficial_crevetor-1.3.2.dist-info/WHEEL
ayla_iot_unofficial_crevetor-1.3.2.dist-info/top_level.txt
ayla_iot_unofficial_crevetor-1.3.2.dist-info/RECORD
