Metadata-Version: 2.1
Name: ayla_iot_unofficial_crevetor
Version: 1.3.2
Summary: Python API for Ayla IoT products (crevetor fork)
Home-page: https://github.com/rewardone/ayla-iot-unofficial
Author: Reward One
Author-email: Crevetor <a.reversat@gmail.com>
Project-URL: Homepage, https://github.com/crevetor/ayla-iot-unofficial
Project-URL: Bug Tracker, https://github.com/crevetor/ayla-iot-unofficial/issues
Classifier: Programming Language :: Python :: 3
Classifier: License :: OSI Approved :: MIT License
Classifier: Operating System :: OS Independent
Requires-Python: >=3.7
License-File: LICENSE
Requires-Dist: aiohttp>=3.8.4
Requires-Dist: requests>=2.31.0
Requires-Dist: ujson>=5.8.0
